navigation_position/__init__.py
navigation_position/example.py
navigation_position/frontend/build/bootstrap.min.css
navigation_position/frontend/build/index.html
navigation_position/frontend/build/assets/index-Do7ZUOIa.js
streamlit_navigation_position-0.0.1.dist-info/METADATA
streamlit_navigation_position-0.0.1.dist-info/WHEEL
streamlit_navigation_position-0.0.1.dist-info/top_level.txt
streamlit_navigation_position-0.0.1.dist-info/RECORD
